irods_fsspec/__init__.py
irods_fsspec/test_irods_fsspec.py
irods_fsspec-0.0.1.dist-info/LICENSE
irods_fsspec-0.0.1.dist-info/METADATA
irods_fsspec-0.0.1.dist-info/WHEEL
irods_fsspec-0.0.1.dist-info/top_level.txt
irods_fsspec-0.0.1.dist-info/RECORD
