Metadata-Version: 2.1
Name: irods-fsspec
Version: 0.0.1
Summary: UNKNOWN
Home-page: UNKNOWN
License: UNKNOWN
Project-URL: Bug Reports, https://github.com/xwcl/irods_fsspec/issues
Platform: UNKNOWN
Requires-Python: >=3.6, <4
License-File: LICENSE
Requires-Dist: fsspec (>=0.8.5)
Requires-Dist: python-irodsclient (>=0.8.6)
